README.md
setup.py
Accounts/__init__.py
Accounts/admin.py
Accounts/apps.py
Accounts/context_processors.py
Accounts/forms.py
Accounts/models.py
Accounts/tests.py
Accounts/urls.py
Accounts/views.py
Accounts/migrations/0001_initial.py
Accounts/migrations/0002_message.py
Accounts/migrations/__init__.py
card/__init__.py
card/admin.py
card/apps.py
card/context_processors.py
card/models.py
card/tests.py
card/urls.py
card/views.py
card/migrations/0001_initial.py
card/migrations/0002_carditem_totals.py
card/migrations/__init__.py
orders/__init__.py
orders/admin.py
orders/apps.py
orders/forms.py
orders/models.py
orders/tests.py
orders/urls.py
orders/views.py
orders/migrations/0001_initial.py
orders/migrations/0002_auto_20220421_1850.py
orders/migrations/__init__.py
phone/__init__.py
phone/admin.py
phone/apps.py
phone/context_processors.py
phone/forms.py
phone/models.py
phone/tests.py
phone/urls.py
phone/views.py
phone/migrations/0001_initial.py
phone/migrations/__init__.py
phonecommerce/__init__.py
phonecommerce/asgi.py
phonecommerce/settings.py
phonecommerce/urls.py
phonecommerce/wsgi.py
phonestore.egg-info/PKG-INFO
phonestore.egg-info/SOURCES.txt
phonestore.egg-info/dependency_links.txt
phonestore.egg-info/requires.txt
phonestore.egg-info/top_level.txt