Metadata-Version: 2.2
Name: phonestore
Version: 0.1
Classifier: Programming Language :: Python :: 3
Classifier: Programming Language :: Python :: 3.8
Classifier: Programming Language :: Python :: 3.9
Classifier: Programming Language :: Python :: 3.10
Requires-Dist: django
Dynamic: classifier
Dynamic: requires-dist
